fixtrate/__init__.py
fixtrate/cli/__init__.py
fixtrate/cli/gen_types.py
fixtrate/cli/main.py
fixtrate/config.py
fixtrate/constants.py
fixtrate/exceptions.py
fixtrate/fix42/__init__.py
fixtrate/fix42/advertisement.py
fixtrate/fix42/allocation.py
fixtrate/fix42/allocation_instruction_ack.py
fixtrate/fix42/bid_request.py
fixtrate/fix42/bid_response.py
fixtrate/fix42/business_message_reject.py
fixtrate/fix42/data.py
fixtrate/fix42/dont_know_trade.py
fixtrate/fix42/email.py
fixtrate/fix42/execution_report.py
fixtrate/fix42/heartbeat.py
fixtrate/fix42/i_o_i.py
fixtrate/fix42/list_cancel_request.py
fixtrate/fix42/list_execute.py
fixtrate/fix42/list_status.py
fixtrate/fix42/list_status_request.py
fixtrate/fix42/list_strike_price.py
fixtrate/fix42/logon.py
fixtrate/fix42/logout.py
fixtrate/fix42/market_data_incremental_refresh.py
fixtrate/fix42/market_data_request.py
fixtrate/fix42/market_data_request_reject.py
fixtrate/fix42/market_data_snapshot_full_refresh.py
fixtrate/fix42/mass_quote.py
fixtrate/fix42/new_order_list.py
fixtrate/fix42/new_order_single.py
fixtrate/fix42/news.py
fixtrate/fix42/order_cancel_reject.py
fixtrate/fix42/order_cancel_replace_request.py
fixtrate/fix42/order_cancel_request.py
fixtrate/fix42/order_status_request.py
fixtrate/fix42/quote.py
fixtrate/fix42/quote_acknowledgement.py
fixtrate/fix42/quote_cancel.py
fixtrate/fix42/quote_request.py
fixtrate/fix42/quote_status_request.py
fixtrate/fix42/reject.py
fixtrate/fix42/resend_request.py
fixtrate/fix42/security_definition.py
fixtrate/fix42/security_definition_request.py
fixtrate/fix42/security_status.py
fixtrate/fix42/security_status_request.py
fixtrate/fix42/sequence_reset.py
fixtrate/fix42/settlement_instructions.py
fixtrate/fix42/test_request.py
fixtrate/fix42/trading_session_status.py
fixtrate/fix42/trading_session_status_request.py
fixtrate/fix42/types.py
fixtrate/fix42/validate.py
fixtrate/fixt/__init__.py
fixtrate/fixt/data.py
fixtrate/fixt/heartbeat.py
fixtrate/fixt/logon.py
fixtrate-0.3.0.post1.dist-info/entry_points.txt
fixtrate-0.3.0.post1.dist-info/WHEEL
fixtrate-0.3.0.post1.dist-info/METADATA
fixtrate-0.3.0.post1.dist-info/RECORD
