Metadata-Version: 2.1
Name: fixtrate
Version: 0.3.0.post1
Summary: Tools for interacting with the FIX protocol.
License: MIT
Author: Carlo Holl
Author-email: carloholl@gmail.com
Requires-Python: >=3.6,<4.0
Classifier: Development Status :: 2 - Pre-Alpha
Classifier: License :: OSI Approved :: MIT License
Classifier: Programming Language :: Python
Classifier: Programming Language :: Python :: 3
Classifier: Programming Language :: Python :: 3.6
Classifier: Programming Language :: Python :: 3.7
Classifier: Programming Language :: Python :: 3.8
Classifier: Programming Language :: Python :: Implementation :: CPython
Requires-Dist: aenum (>=2.1.2)
Requires-Dist: aioredis (>=1.1.0)
Requires-Dist: async-timeout (>=2.0)
Requires-Dist: python-dateutil (>=2.6.1)
Requires-Dist: simplefix (>=1.0.12)
Requires-Dist: sortedcontainers (>=2.2.2,<3.0.0)
Requires-Dist: typing_extensions (>=3.7.4,<4.0.0)
Requires-Dist: untangle (>=1.1.1)
